hangul_names/__init__.py
hangul_names/defs.py
hangul_names/transliterator.py
hangul_names/words.py
hangul_names/dramawiki/__init__.py
hangul_names/dramawiki/rules.py
hangul_names-0.4.2.dist-info/LICENSE
hangul_names-0.4.2.dist-info/METADATA
hangul_names-0.4.2.dist-info/WHEEL
hangul_names-0.4.2.dist-info/top_level.txt
hangul_names-0.4.2.dist-info/RECORD
