Metadata-Version: 2.1
Name: hangul-names
Version: 0.4.2
Summary: Convert Korean people's Hangul names to romanized versions
Home-page: https://gitlab.com/venture-forth/hangul-names/
Author: Melvyn Sopacua
Author-email: 2403540-melvyn-sopacua@users.noreply.gitlab.com
License: BSD-2-Clause
Keywords: Korean,Hangul,romanization,transliteration
Platform: UNKNOWN
